funtools/__init__.py
funtools/_plot
funtools/backup/__init__.py
funtools/backup/bathy_modification.py
funtools/backup/bokeh.py
funtools/backup/buffer_fill_poly.py
funtools/backup/create_scatter_poly.py
funtools/backup/datum.py
funtools/backup/error.py
funtools/backup/geo.py
funtools/backup/geometry.py
funtools/backup/grid.py
funtools/backup/interpolate.py
funtools/backup/misc.py
funtools/backup/parabatch.py
funtools/backup/parallel.py
funtools/backup/parse_raw_data.py
funtools/backup/pbs.py
funtools/backup/polyfilter.py
funtools/backup/simulation.py
funtools/backup/smooth.py
funtools/backup/spectrum.py
funtools/backup/station_plotter.py
funtools/backup/stations.py
funtools/backup/structure.py
funtools/backup/subgrid.py
funtools/backup/transform.py
funtools/io/__init__.py
funtools/io/field.py
funtools/io/input.py
funtools/io/log.py
funtools/io/stations.py
funtools/math/__init__.py
funtools/math/geometry.py
funtools/math/grid.py
funtools/math/projection.py
funtools/math/signal.py
funtools/math/waves.py
funtools/model/__init__.py
funtools/model/simulation.py
funtools/model/stations.py
funtools/parallel/__init__.py
funtools/parallel/cluster.py
funtools/parallel/dashboard.py
funtools/parallel/multi.py
funtools/parallel/mydask.py
funtools/parallel/simple.py
funtools/ui/__init__.py
funtools/ui/colorbar.py
funtools/ui/colormaps.py
funtools/ui/config/__init__.py
funtools/ui/config/core.py
funtools/ui/config/elements.py
funtools/ui/config/objects.py
funtools/ui/config/plots.py
funtools/ui/forms.py
funtools/ui/link/__init__.py
funtools/ui/link/core.py
funtools/ui/link/hvbokeh.py
funtools/ui/link/padbox.js
funtools/ui/link/padbox.py
funtools/ui/link/vrectagle.py
funtools/ui/models/__init__.py
funtools/ui/models/funwave/__init__.py
funtools/ui/models/funwave/driver.py
funtools/ui/models/funwave/viewer.py
funtools/ui/widgets.py
funtools/ui/widgets2.py
funwavetools-0.2.1.dist-info/METADATA
funwavetools-0.2.1.dist-info/WHEEL
funwavetools-0.2.1.dist-info/RECORD
