Metadata-Version: 2.1
Name: funwavetools
Version: 0.2.1
Summary: Pre/Post processing code for FUNWAVE simulations
License: BSD-2-Clause
Keywords: funwave-tvd
Author: Michael-Angelo Y.-H. Lam
Author-email: michael.y.lam@erdc.dren.mil
Maintainer: Michael-Angelo Y.-H. Lam
Maintainer-email: michaelangelo.yh.lam@gmail.com
Requires-Python: >=3.10.4,<4.0.0
Classifier: License :: OSI Approved :: BSD License
Classifier: Programming Language :: Python :: 3
Classifier: Programming Language :: Python :: 3.11
Classifier: Programming Language :: Python :: 3.12
Classifier: Programming Language :: Python :: 3.13
Requires-Dist: bokeh (>=3.5.0,<4.0.0)
Requires-Dist: cmocean (>=4.0.3,<5.0.0)
Requires-Dist: dask[distributed] (>=2025.5.1,<2026.0.0)
Requires-Dist: holoviews (>=1.19.1,<2.0.0)
Requires-Dist: jupyter-bokeh (>=4.0.5,<5.0.0)
Requires-Dist: jupyterlab (>=4.0.5,<5.0.0)
Requires-Dist: notebook (>=7.2.1,<8.0.0)
Requires-Dist: numpy (>=2.0.0,<3.0.0)
Requires-Dist: pandas (>=2.2.2,<3.0.0)
Requires-Dist: panel (>=1.5.3,<2.0.0)
Requires-Dist: plotly (>=5.24.1,<6.0.0)
Requires-Dist: pyproj (>=3.6.1,<4.0.0)
Requires-Dist: rasterio (>=1.3.10,<2.0.0)
Requires-Dist: scipy (>=1.14.0,<2.0.0)
Requires-Dist: selenium (>=4.26.1,<5.0.0)
Requires-Dist: shapely (>=2.0.3,<3.0.0)
Requires-Dist: shapelysmooth (>=0.2.1,<0.3.0)
Requires-Dist: tqdm (>=4.66.4,<5.0.0)
Requires-Dist: webdriver-manager (>=4.0.2,<5.0.0)
